mcp_kql_server/__init__.py
mcp_kql_server/__main__.py
mcp_kql_server/constants.py
mcp_kql_server/execute_kql.py
mcp_kql_server/kql_auth.py
mcp_kql_server/mcp_server.py
mcp_kql_server/memory.py
mcp_kql_server/utils.py
mseep_mcp_kql_server-2.0.6.dist-info/METADATA
mseep_mcp_kql_server-2.0.6.dist-info/WHEEL
mseep_mcp_kql_server-2.0.6.dist-info/RECORD
